[
  {
    "id": 1735989600000,
    "name": "Phone Stand - Basic",
    "filamentType": "PLA",
    "customDensity": 1.20,
    "filamentDiameter": 1.75,
    "filamentLength": 5.2,
    "filamentPrice": 450,
    "filamentWeight": 1,
    "printTime": 2.5,
    "hourlyRate": 50,
    "markup": 15,
    "printerPower": 350,
    "electricityRate": 3.50,
    "maintenanceCostPerHour": 8.50,
    "materialCost": 7.02,
    "laborCost": 125.00,
    "operationalCost": 23.13,
    "finalPrice": 178.38,
    "profit": 23.23,
    "createdAt": "2025-01-04T12:00:00.000Z"
  },
  {
    "id": 1735989600001,
    "name": "Miniature Figure",
    "filamentType": "ABS",
    "customDensity": 1.20,
    "filamentDiameter": 1.75,
    "filamentLength": 12.8,
    "filamentPrice": 480,
    "filamentWeight": 1,
    "printTime": 4.0,
    "hourlyRate": 50,
    "markup": 20,
    "printerPower": 350,
    "electricityRate": 3.50,
    "maintenanceCostPerHour": 8.50,
    "materialCost": 16.13,
    "laborCost": 200.00,
    "operationalCost": 46.00,
    "finalPrice": 314.56,
    "profit": 52.43,
    "createdAt": "2025-01-04T12:30:00.000Z"
  },
  {
    "id": 1735989600002,
    "name": "Custom Bracket",
    "filamentType": "PETG",
    "customDensity": 1.20,
    "filamentDiameter": 1.75,
    "filamentLength": 3.1,
    "filamentPrice": 520,
    "filamentWeight": 1,
    "printTime": 1.5,
    "hourlyRate": 75,
    "markup": 25,
    "printerPower": 350,
    "electricityRate": 3.50,
    "maintenanceCostPerHour": 8.50,
    "materialCost": 5.09,
    "laborCost": 112.50,
    "operationalCost": 18.00,
    "finalPrice": 169.49,
    "profit": 33.90,
    "createdAt": "2025-01-04T13:00:00.000Z"
  },
  {
    "id": 1735989600003,
    "name": "Desk Organizer",
    "filamentType": "PLA",
    "customDensity": 1.20,
    "filamentDiameter": 1.75,
    "filamentLength": 15.6,
    "filamentPrice": 450,
    "filamentWeight": 1,
    "printTime": 6.0,
    "hourlyRate": 60,
    "markup": 30,
    "printerPower": 350,
    "electricityRate": 3.50,
    "maintenanceCostPerHour": 8.50,
    "materialCost": 21.06,
    "laborCost": 360.00,
    "operationalCost": 72.00,
    "finalPrice": 588.98,
    "profit": 135.92,
    "createdAt": "2025-01-04T14:00:00.000Z"
  },
  {
    "id": 1735989600004,
    "name": "Key Chain",
    "filamentType": "TPU",
    "customDensity": 1.20,
    "filamentDiameter": 1.75,
    "filamentLength": 0.8,
    "filamentPrice": 580,
    "filamentWeight": 1,
    "printTime": 0.5,
    "hourlyRate": 40,
    "markup": 50,
    "printerPower": 350,
    "electricityRate": 3.50,
    "maintenanceCostPerHour": 8.50,
    "materialCost": 1.56,
    "laborCost": 20.00,
    "operationalCost": 6.00,
    "finalPrice": 41.34,
    "profit": 13.78,
    "createdAt": "2025-01-04T15:00:00.000Z"
  }
]